README
cwltool_service.py
setup.py
cwltool_service.egg-info/PKG-INFO
cwltool_service.egg-info/SOURCES.txt
cwltool_service.egg-info/dependency_links.txt
cwltool_service.egg-info/entry_points.txt
cwltool_service.egg-info/requires.txt
cwltool_service.egg-info/top_level.txt
cwltool_service.egg-info/zip-safe