Metadata-Version: 1.1
Name: cwltool-service
Version: 1.0
Summary: Common workflow language runner service
Home-page: https://github.com/common-workflow-language/common-workflow-language
Author: Common workflow language working group
Author-email: common-workflow-language@googlegroups.com
License: Apache 2.0
Download-URL: https://github.com/common-workflow-language/common-workflow-language
Platform: UNKNOWN
